Workbook

Sheet Expenses
A1: Date | B1: Description | C1: Category | D1: Amount (R)
A2: 46204 | B2: Rent - Unit 4, Industria | C2: Rent | D2: 12000
A3: 05/07/2026 | B3: Eskom prepaid electricity | C3: Electricity | D3: 1 850,00
A4: 07/07/2026 | B4: Telkom fibre - July | C4: Internet | D4: R899.00
A5: 15/07/2026 | B5: Engen - delivery van fuel | C5: Fuel | D5: 1 240,50
A7: 46235 | B7: Rent - Unit 4, Industria | C7: Rent | D7: 12000
A8: 06/08/2026 | B8: Eskom prepaid electricity | C8: Electricity | D8: 2 010,00
A9: 07/08/2026 | B9: Telkom fibre - August | C9: Internet | D9: 899
A10: 18/08/2026 | B10: Facebook ads - spring promo | C10: Marketing | D10: 1,500.00
A11: 21/08/2026 | B11: Refund - Telkom overcharge | C11: Internet | D11: (99,00)
A12: 46266 | B12: Rent - Unit 4, Industria | C12: Rent | D12: 12000
A13: 05/09/2026 | B13: Eskom prepaid electricity | C13: Electricity | D13: 1 920,00
A14: 07/09/2026 | B14: Telkom fibre - September | C14: Internet | D14: 899
B15: TOTAL (numeric cells only) | D15: =SUM(D2:D14) -> 37798
A17: Typed by hand over the quarter: mixed date styles, SA and US number formats, a blank row, a refund in brackets and a totals row, the way real old books look.

Sheet Notes
A1: Item | B1: Value
A2: Business | B2: Karoo Coffee Roasters (Pty) Ltd (fictional test company)
A3: VAT number | B3: 4123456789
A4: VAT rate | B4: 0.15
A5: Opening bank balance 1 Jul 2026 (R) | B5: 80000
A6: Bank | B6: FNB Business Cheque
A7: Invoice terms (days) | B7: 30
A9: How to use | B9: Blue cells are inputs. Ex VAT, VAT and Total are formulas.
A10: Source | B10: All figures are made up for testing Nexus Ledger.

Sheet Categories
A1: Category | B1: Ledger account code | C1: Ledger account
A2: Rent | B2: 6100 | C2: Rent
A3: Electricity | B3: 6200 | C3: Electricity & Water
A4: Internet | B4: 6300 | C4: Telephone & Internet
A5: Fuel | B5: 6600 | C5: Fuel & Travel
A6: Marketing | B6: 6800 | C6: Marketing & Advertising

Sheet Contacts
A1: Name | B1: Type | C1: Email | D1: Phone
A2: Bean There Cafe | B2: CUSTOMER | C2: accounts@beanthere.example | D2: 0215550101
A3: Stellenbosch Deli | B3: CUSTOMER | C3: admin@stbdeli.example | D3: 0215550144
A4: Hotel Breede | B4: CUSTOMER | C4: finance@hotelbreede.example | D4: 0235550199
A5: Green Bean Importers | B5: SUPPLIER | C5: billing@greenbean.example | D5: 0115550123
A6: PackRight Packaging | B6: SUPPLIER | C6: ar@packright.example | D6: 0315550177

Sheet Sales
A1: Date | B1: Ref | C1: Customer | D1: Item | E1: Qty | F1: Unit price ex VAT | G1: Ex VAT | H1: VAT | I1: Total | J1: Paid on | K1: Amount paid | L1: Credit note qty | M1: Note
A2: 46206 | B2: S1 | C2: Bean There Cafe | D2: Espresso blend 1kg | E2: 40 | F2: 320 | G2: =E2*F2 -> 12800 | H2: =ROUND(G2*Notes!$B$4,2) -> 1920 | I2: =G2+H2 -> 14720 | J2: 46223 | K2: =I2-IF(L2="",0,L2*F2*(1+Notes!$B$4)) -> 14720 | M2: Paid in full
A3: 46213 | B3: S2 | C3: Stellenbosch Deli | D3: House blend 1kg | E3: 25 | F3: 330 | G3: =E3*F3 -> 8250 | H3: =ROUND(G3*Notes!$B$4,2) -> 1237.5 | I3: =G3+H3 -> 9487.5 | J3: 46239 | K3: 5000 | M3: Part payment, rest still owing
A4: 46238 | B4: S3 | C4: Hotel Breede | D4: Filter blend 1kg | E4: 60 | F4: 300 | G4: =E4*F4 -> 18000 | H4: =ROUND(G4*Notes!$B$4,2) -> 2700 | I4: =G4+H4 -> 20700 | J4: 46264 | K4: =I4-IF(L4="",0,L4*F4*(1+Notes!$B$4)) -> 18975 | L4: 5 | M4: 5 bags damaged in delivery: credit note 12 Aug
A5: 46267 | B5: S4 | C5: Bean There Cafe | D5: Espresso blend 1kg | E5: 40 | F5: 320 | G5: =E5*F5 -> 12800 | H5: =ROUND(G5*Notes!$B$4,2) -> 1920 | I5: =G5+H5 -> 14720 | M5: Unpaid, due 2 Oct (overdue)
A6: 46275 | B6: Q1 | C6: Stellenbosch Deli | D6: Espresso machine service | E6: 1 | F6: 2500 | G6: =E6*F6 -> 2500 | H6: =ROUND(G6*Notes!$B$4,2) -> 375 | I6: =G6+H6 -> 2875 | J6: 46290 | K6: =I6-IF(L6="",0,L6*F6*(1+Notes!$B$4)) -> 2875 | M6: Started as a quote, accepted, converted

Sheet Purchases
A1: Date | B1: Ref | C1: Supplier | D1: Item | E1: Qty | F1: Unit price ex VAT | G1: Ex VAT | H1: VAT | I1: Total | J1: Paid on | K1: Account code
A2: 46204 | B2: P1 | C2: Green Bean Importers | D2: Green beans Ethiopia 60kg bag | E2: 5 | F2: 5700 | G2: =E2*F2 -> 28500 | H2: =ROUND(G2*Notes!$B$4,2) -> 4275 | I2: =G2+H2 -> 32775 | J2: 46218 | K2: 5000
A3: 46235 | B3: P2 | C3: Green Bean Importers | D3: Green beans Brazil 60kg bag | E3: 4 | F3: 4900 | G3: =E3*F3 -> 19600 | H3: =ROUND(G3*Notes!$B$4,2) -> 2940 | I3: =G3+H3 -> 22540 | J3: 46254 | K3: 5000
A4: 46242 | B4: P3 | C4: PackRight Packaging | D4: Valve coffee bags 1kg | E4: 2000 | F4: 2.1 | G4: =E4*F4 -> 4200 | H4: =ROUND(G4*Notes!$B$4,2) -> 630 | I4: =G4+H4 -> 4830 | K4: 5000

Sheet Bank other
A1: Date | B1: Description on statement | C1: Money in | D1: Money out | E1: Account code
A2: 46234 | B2: FNB SERVICE FEE | D2: 185 | E2: 6400
A3: 46265 | B3: FNB SERVICE FEE | D3: 185 | E3: 6400
A4: 46277 | B4: CASH DEP MARKET DAY | C4: 500 | E4: 4100
A5: 46295 | B5: FNB SERVICE FEE | D5: 185 | E5: 6400
